PyPXE-1.7.3.dist-info/DESCRIPTION.rst
PyPXE-1.7.3.dist-info/METADATA
PyPXE-1.7.3.dist-info/RECORD
PyPXE-1.7.3.dist-info/WHEEL
PyPXE-1.7.3.dist-info/entry_points.txt
PyPXE-1.7.3.dist-info/metadata.json
PyPXE-1.7.3.dist-info/top_level.txt
pypxe/__init__.py
pypxe/dhcp.py
pypxe/helpers.py
pypxe/http.py
pypxe/server.py
pypxe/tftp.py
pypxe/nbd/__init__.py
pypxe/nbd/nbd.py
pypxe/nbd/writes.py
