Metadata-Version: 2.0
Name: PyPXE
Version: 1.7.3
Summary: Pure Python2 PXE (DHCP-(Proxy)/TFTP/HTTP/NBD) Server
Home-page: https://github.com/pypxe/PyPXE
Author: UNKNOWN
Author-email: UNKNOWN
License: MIT
Platform: UNKNOWN
